odoo/addons/project_task_restrict_stage_changes/README.rst
odoo/addons/project_task_restrict_stage_changes/__init__.py
odoo/addons/project_task_restrict_stage_changes/__manifest__.py
odoo/addons/project_task_restrict_stage_changes/i18n/ca_ES.po
odoo/addons/project_task_restrict_stage_changes/i18n/es.po
odoo/addons/project_task_restrict_stage_changes/models/__init__.py
odoo/addons/project_task_restrict_stage_changes/models/project_task.py
odoo/addons/project_task_restrict_stage_changes/models/project_task_type.py
odoo/addons/project_task_restrict_stage_changes/readme/CONFIGURE.rst
odoo/addons/project_task_restrict_stage_changes/readme/CONTRIBUTORS.rst
odoo/addons/project_task_restrict_stage_changes/readme/DESCRIPTION.rst
odoo/addons/project_task_restrict_stage_changes/readme/USAGE.rst
odoo/addons/project_task_restrict_stage_changes/security/project_task_restrict_stage_changes_security.xml
odoo/addons/project_task_restrict_stage_changes/static/description/icon.png
odoo/addons/project_task_restrict_stage_changes/static/description/index.html
odoo/addons/project_task_restrict_stage_changes/tests/__init__.py
odoo/addons/project_task_restrict_stage_changes/tests/test_project_task_restrict_stage_changes.py
odoo/addons/project_task_restrict_stage_changes/views/project_task_type_views.xml
odoo_addon_project_task_restrict_stage_changes-16.0.1.0.0.1.dist-info/METADATA
odoo_addon_project_task_restrict_stage_changes-16.0.1.0.0.1.dist-info/WHEEL
odoo_addon_project_task_restrict_stage_changes-16.0.1.0.0.1.dist-info/top_level.txt
odoo_addon_project_task_restrict_stage_changes-16.0.1.0.0.1.dist-info/RECORD
