Metadata-Version: 2.1
Name: odoo-addon-project_task_restrict_stage_changes
Version: 16.0.1.0.0.1
Summary: Configure task stages restricted to a user group
Home-page: https://github.com/sygel-technology/sy-project
Author: Sygel
License: AGPL-3
Classifier: Programming Language :: Python
Classifier: Framework :: Odoo
Classifier: Framework :: Odoo :: 16.0
Classifier: License :: OSI Approved :: GNU Affero General Public License v3
Requires-Python: >=3.10
Requires-Dist: odoo<16.1dev,>=16.0a
